CONTRIBUTORS
MANIFEST.in
README.md
setup.py
hcls_fhir_rdf/__init__.py
hcls_fhir_rdf/defaults.py
hcls_fhir_rdf/fhir_elements.py
hcls_fhir_rdf/fhir_types.py
hcls_fhir_rdf/namespaces.py
hcls_fhir_rdf/rdflib_formats.py
hcls_fhir_rdf/utils.py
hcls_fhir_rdf.egg-info/PKG-INFO
hcls_fhir_rdf.egg-info/SOURCES.txt
hcls_fhir_rdf.egg-info/dependency_links.txt
hcls_fhir_rdf.egg-info/requires.txt
hcls_fhir_rdf.egg-info/top_level.txt
scripts/download_fhir_spec
scripts/generate_rdf
scripts/generate_shex
scripts/generate_xml_definitions
share/xsl/transform.xsl