Metadata-Version: 1.1
Name: hcls-fhir-rdf
Version: 0.1.3
Summary: FHIR to RDF conversion tools
Home-page: http://github.com/w3c/hcls-fhir-rdf
Author: Harold Solbrig
Author-email: solbrig.harold@mayo.edu
License: BSD 3-Clause license
Platform: UNKNOWN
Classifier: Development Status :: 4 - Beta
Classifier: Environment :: Console
Classifier: Environment :: Web Environment
Classifier: Intended Audience :: Developers
Classifier: License :: OSI Approved :: BSD License
Classifier: Operating System :: OS Independent
Classifier: Programming Language :: Python
Classifier: Topic :: Internet
Classifier: Topic :: Software Development :: Libraries
Classifier: Programming Language :: Python :: 3
Classifier: Programming Language :: Python :: 3 :: Only
Provides: hcls_fhir_rdf
